setup.cfg
setup.py
py_wrapi/__init__.py
py_wrapi/authenticate.py
py_wrapi/gmail_resource_mapping.py
py_wrapi/gmail_wrapper.py
py_wrapi/gsheets_resource_mapping.py
py_wrapi/gsheets_wrapper.py
py_wrapi/printers.py
py_wrapi/sently_resource_mapping.py
py_wrapi/sently_wrapper.py
py_wrapi/spotify_resource_mapping.py
py_wrapi/spotify_wrapper.py
py_wrapi/youtube_resource_mapping.py
py_wrapi/youtube_wrapper.py
py_wrapi.egg-info/PKG-INFO
py_wrapi.egg-info/SOURCES.txt
py_wrapi.egg-info/dependency_links.txt
py_wrapi.egg-info/not-zip-safe
py_wrapi.egg-info/requires.txt
py_wrapi.egg-info/top_level.txt